exec_hints.py
exec_hints-0.1.4.dist-info/LICENSE
exec_hints-0.1.4.dist-info/WHEEL
exec_hints-0.1.4.dist-info/METADATA
exec_hints-0.1.4.dist-info/RECORD
