Metadata-Version: 2.1
Name: exec_hints
Version: 0.1.4
Summary: Pretty comprehensive typehint evaluator, gives your Python functions that extra bit of zazz and illegibility they always needed.
Author: LiquidPulsar
Project-URL: Home, https://github.com/LiquidPulsar/exec_hints
